{"Content-Type": "image/png", "Content-Length": "32836", "Connection": "close", "x-amz-id-2": "EEVBfovm9MRHduqm6/KZ6AnZS+p64HNxhHbg8j8QLolIPmSSAfoAY0b0HdRJO+T4lXRUU7X9HJw=", "x-amz-request-id": "8B1QYCFMW5JDYHHS", "Date": "Mon, 10 Jul 2023 14:45:02 GMT", "x-amz-replication-status": "COMPLETED", "Last-Modified": "Sat, 15 Apr 2023 23:32:53 GMT", "ETag": "\"0b6e21ddd3eeba748e8c3d390f57425f\"", "x-amz-server-side-encryption": "AES256", "x-amz-version-id": "DIn194KkYQ8TXu6bR11Cs5ycIJx0EoVs", "Accept-Ranges": "bytes", "Server": "AmazonS3", "Content-Security-Policy": "default-src 'none'; style-src 'unsafe-inline'; img-src https://*/favicon.ico; sandbox", "Access-Control-Allow-Origin": "*", "X-Robots-Tag": "none", "Content-Disposition": "inline; filename=\"Imagefromcommons.wikimedia.orgon2023-04-15at7.32.39PM.png\"", "X-Xss-Protection": "1; mode=block", "X-Content-Type-Options": "nosniff", "Referrer-Policy": "no-referrer", "Cache-Control": "max-age=14400, immutable", "X-Cache": "Miss from cloudfront", "Via": "1.1 7d30b02170e051a5fc315a8f4ba8c20c.cloudfront.net (CloudFront)", "X-Amz-Cf-Pop": "IAD55-P1", "X-Amz-Cf-Id": "dC1NJ9E64VDzXw8iauRGvnMtRI_BYkCeEQedFA5RVXsovHLiZHDvKg=="}