{"records":[{"id":"recxlAWvQ36aAvb1q","createdTime":"2022-04-24T21:02:15.000Z","fields":{"term":"cazadora","xml-lang":"es","feature_values_display_name_en":["recVh9T90I9VMfWQJ"],"AATID":300046143,"feature_values_id":["CC00106"]}},{"id":"recxnMTN6T3ISFizj","createdTime":"2022-04-24T21:02:15.000Z","fields":{"term":"莎爾瓦","xml-lang":"zh-hant","feature_values_display_name_en":["rec0n3CQTd0Ju6E0A"],"AATID":300216954,"feature_values_id":["CC00434"]}},{"id":"recxuMAGVhkKssRyp","createdTime":"2022-04-24T21:02:15.000Z","fields":{"term":"裙襬","xml-lang":"zh-hant","feature_values_display_name_en":["recAl2FHmINxWCdqu"],"AATID":300224243,"feature_values_id":["CC00194"]}},{"id":"recxvGC6gtmLLzt2Z","createdTime":"2022-04-24T21:02:15.000Z","fields":{"term":"buckle (strap accessory)","xml-lang":"en","feature_values_display_name_en":["rec6CMD16b7QAicDW"],"AATID":300239260,"feature_values_id":["CC00001"]}},{"id":"recxyk9Pf2A5bVkU2","createdTime":"2022-04-24T21:02:15.000Z","fields":{"term":"pencil suknje","xml-lang":"sr","feature_values_display_name_en":["reckE0QZ3EEqD24w8"],"AATID":300411738,"feature_values_id":["CC00180"]}},{"id":"recxzdQN0taUh4Tab","createdTime":"2022-04-24T21:02:15.000Z","fields":{"term":"jupes (garments)","xml-lang":"fr","feature_values_display_name_en":["receEOQdjPyVanseM"],"AATID":300209932,"feature_values_id":["CC00341"]}},{"id":"recy0KOmQh2tLglmk","createdTime":"2022-04-24T21:02:15.000Z","fields":{"term":"Hemd","xml-lang":"de","feature_values_display_name_en":["recFfCQnHbKVETSUW"],"AATID":300212499,"feature_values_id":["CC00340"]}},{"id":"recy0VDGKPbSuotfs","createdTime":"2022-04-24T21:02:15.000Z","fields":{"term":"engageantes","xml-lang":"nl","feature_values_display_name_en":["recB55Z1s86uBEZ93"],"AATID":300253720,"feature_values_id":["CC00327"]}},{"id":"recy1qO9fHmZeWFw3","createdTime":"2022-04-24T21:02:15.000Z","fields":{"term":"肩墊","xml-lang":"zh-hant","feature_values_display_name_en":["recWnFTXffzwliXvs"],"AATID":300210527,"feature_values_id":["CC00398"]}},{"id":"recy2E4GJpTIXsoum","createdTime":"2022-04-24T21:02:15.000Z","fields":{"term":"pluviale","xml-lang":"nl","feature_values_display_name_en":["recxhECWGGbB9calH"],"AATID":300210429,"feature_values_id":["CC00448"]}},{"id":"recy4jBrbUgtbMRSy","createdTime":"2022-04-24T21:02:15.000Z","fields":{"term":"ενδύματα σε στυλ ρεντινγκότας (φορέματα)","xml-lang":"el","feature_values_display_name_en":["recKJZd24Eo9U3iqR"],"AATID":300254632,"feature_values_id":["CC00503"]}},{"id":"recy6Uf4p0x9GGbG5","createdTime":"2022-04-24T21:02:15.000Z","fields":{"term":"epolete","xml-lang":"sr","feature_values_display_name_en":["rec135mWCRBOAbArD"],"AATID":300224235,"feature_values_id":["CC00395"]}},{"id":"recyHDmajjGCBpn6V","createdTime":"2022-04-24T21:02:15.000Z","fields":{"term":"camiseta sin espalda","xml-lang":"es","feature_values_display_name_en":["recs50GdTMa3IT5jm"],"AATID":300209885,"feature_values_id":["CC00016"]}},{"id":"recyHj2lx0bBR2o9I","createdTime":"2022-04-24T21:02:15.000Z","fields":{"term":"τουρνούρι","xml-lang":"el","feature_values_display_name_en":["recd5BBfSyMMfEHwX"],"AATID":300210580,"feature_values_id":["CC00104"]}},{"id":"recyJh33AdJJHXtfD","createdTime":"2022-04-24T21:02:15.000Z","fields":{"term":"Sarong","xml-lang":"de","feature_values_display_name_en":["recxQiO5HRTf5oVWk"],"AATID":300209928,"feature_values_id":["CC00179"]}},{"id":"recyKW2CWIo7yJftg","createdTime":"2022-04-24T21:02:15.000Z","fields":{"term":"scialle","xml-lang":"it","feature_values_display_name_en":["recgncT8SlL3urVSR"],"AATID":300209991,"feature_values_id":["CC00046"]}},{"id":"recyPDTZPd7VW34eq","createdTime":"2022-04-24T21:02:15.000Z","fields":{"term":"calzature","xml-lang":"it","feature_values_display_name_en":["recCwLz1maAyCooRN"],"AATID":300209280,"feature_values_id":["CC00603"]}},{"id":"recyQ94guJVLptgxU","createdTime":"2022-04-24T21:02:15.000Z","fields":{"term":"mantuas","xml-lang":"en","feature_values_display_name_en":["recFqBsag2vTfdl82"],"AATID":300209837,"feature_values_id":["CC00113"]}},{"id":"recyTzjcwGXVzWGMY","createdTime":"2022-04-24T21:02:15.000Z","fields":{"term":"家常褲","xml-lang":"zh-hant","feature_values_display_name_en":["rechoefNv4f2S5IOZ"],"AATID":300209934,"feature_values_id":["CC00435"]}},{"id":"recyTzmN03LTt8lmj","createdTime":"2022-04-24T21:02:15.000Z","fields":{"term":"hanging sleeves","xml-lang":"es","feature_values_display_name_en":["rec0Mg0rSiOsWlQLF"],"AATID":300253738,"feature_values_id":["CC00150"]}},{"id":"recyUGz59UuwT3Ip3","createdTime":"2022-04-24T21:02:15.000Z","fields":{"term":"sportbroek","xml-lang":"nl","feature_values_display_name_en":["recsPjVPSsbQnSamC"],"AATID":300257544,"feature_values_id":["CC00438"]}},{"id":"recyWC9exeKUhSRlZ","createdTime":"2022-04-24T21:02:15.000Z","fields":{"term":"nakit","xml-lang":"sr","feature_values_display_name_en":["recdIdFAfKOZO5syH"],"AATID":300209286,"feature_values_id":["CC00610"]}},{"id":"recyYJGQFX7gFQadT","createdTime":"2022-04-24T21:02:15.000Z","fields":{"term":"suit (main garment)","xml-lang":"en","feature_values_display_name_en":["recHQv0c54BZewoTd"],"AATID":300209863,"feature_values_id":["CC00342"]}},{"id":"recyZBEKFdBocJGmC","createdTime":"2022-04-24T21:02:15.000Z","fields":{"term":"Unterrock","xml-lang":"de","feature_values_display_name_en":["recJW1uF3YDhOzCvt"],"AATID":300210564,"feature_values_id":["CC00123"]}},{"id":"recyZoRsGGbK0o68A","createdTime":"2022-04-24T21:02:15.000Z","fields":{"term":"bolero","xml-lang":"es","feature_values_display_name_en":["recqRH6vx25wNqk8I"],"AATID":300209876,"feature_values_id":["CC00155"]}},{"id":"recyaSHR8IZQI4dTg","createdTime":"2022-04-24T21:02:15.000Z","fields":{"term":"μπλούζες","xml-lang":"el","feature_values_display_name_en":["recJZVAilkpc2N2C5"],"AATID":300046133,"feature_values_id":["CC00337"]}},{"id":"recydqUZiRNILijzB","createdTime":"2022-04-24T21:02:15.000Z","fields":{"term":"lavallières","xml-lang":"fr","feature_values_display_name_en":["recUKFXvcw2X7Ttud"],"AATID":300210052,"feature_values_id":["CC00028"]}},{"id":"recyidFddnqiuHIUi","createdTime":"2022-04-24T21:02:15.000Z","fields":{"term":"handkerchiefs","xml-lang":"en","feature_values_display_name_en":["receuMB99dD1mjQjb"],"AATID":300216195,"feature_values_id":["CC00172"]}},{"id":"recyjuzgkvTQTGvmQ","createdTime":"2022-04-24T21:02:15.000Z","fields":{"term":"Überkleider (Oberbekleidungen)","xml-lang":"de","feature_values_display_name_en":["recV7mrJtYQ4Kn7ii"],"AATID":300209265,"feature_values_id":["CC00458"]}},{"id":"recykifMdOtfniVti","createdTime":"2022-04-24T21:02:15.000Z","fields":{"term":"jasjes","xml-lang":"nl","feature_values_display_name_en":["recba5R3kW5Aapd17"],"AATID":300046167,"feature_values_id":["CC00339"]}},{"id":"recymRBb1xhYiAdmD","createdTime":"2022-04-24T21:02:15.000Z","fields":{"term":"ascot","xml-lang":"en","feature_values_display_name_en":["recUKFXvcw2X7Ttud"],"AATID":300210052,"feature_values_id":["CC00028"]}},{"id":"recymfNCHo4m7wfIH","createdTime":"2022-04-24T21:02:15.000Z","fields":{"term":"dresses, wedding","xml-lang":"en","feature_values_display_name_en":["rec1wGCGk0CNn2XsE"],"AATID":300255177,"feature_values_id":["CC00379"]}},{"id":"recyp1RMEuRVfkDmV","createdTime":"2022-04-24T21:02:15.000Z","fields":{"term":"pantalón de tiro corto","xml-lang":"es","feature_values_display_name_en":["recqL4LaXuDINk25e"],"AATID":300221446,"feature_values_id":["CC00425"]}},{"id":"recypwfCNEEoWCZSq","createdTime":"2022-04-24T21:02:15.000Z","fields":{"term":"chāo duǎn kù","xml-lang":"zh-latn-pinyin-x-hanyu","feature_values_display_name_en":["recclI1uaIHLgPqww"],"AATID":300221447,"feature_values_id":["CC00440"]}},{"id":"recyqw8b8H8jzmkza","createdTime":"2022-04-24T21:02:15.000Z","fields":{"term":"slips (underwear)","xml-lang":"en","feature_values_display_name_en":["recJW1uF3YDhOzCvt"],"AATID":300210564,"feature_values_id":["CC00123"]}},{"id":"recyrybyQOai1CDsh","createdTime":"2022-04-24T21:02:15.000Z","fields":{"term":"fibbia","xml-lang":"it","feature_values_display_name_en":["rec6CMD16b7QAicDW"],"AATID":300239260,"feature_values_id":["CC00001"]}},{"id":"recysAsbVO38IAlwh","createdTime":"2022-04-24T21:02:15.000Z","fields":{"term":"αγκράφα","xml-lang":"el","feature_values_display_name_en":["rec6CMD16b7QAicDW"],"AATID":300239260,"feature_values_id":["CC00001"]}},{"id":"recyvmSnpEaRzK9I9","createdTime":"2022-04-24T21:02:15.000Z","fields":{"term":"omslagdoek","xml-lang":"nl","feature_values_display_name_en":["recgncT8SlL3urVSR"],"AATID":300209991,"feature_values_id":["CC00046"]}},{"id":"recyw5Yyg0rt6gIh3","createdTime":"2022-04-24T21:02:15.000Z","fields":{"term":"bottoni","xml-lang":"it","feature_values_display_name_en":["recfFfiUQiol5Irzt"],"AATID":300239261,"feature_values_id":["CC00002"]}},{"id":"recyx1G7sBjhfrYM8","createdTime":"2022-04-24T21:02:15.000Z","fields":{"term":"odeća za veče","xml-lang":"sr","feature_values_display_name_en":["reccR3cmdiqVRw4RT"],"AATID":300224227,"feature_values_id":["CC00370"]}},{"id":"recyxLOHXab6WIvT6","createdTime":"2022-04-24T21:02:15.000Z","fields":{"term":"lencería","xml-lang":"es","feature_values_display_name_en":["recc1cerFomfG5LYa"],"AATID":300211604,"feature_values_id":["CC00519"]}},{"id":"recyyGSGY0SsXZFRX","createdTime":"2022-04-24T21:02:15.000Z","fields":{"term":"robe redingote","xml-lang":"fr","feature_values_display_name_en":["recKJZd24Eo9U3iqR"],"AATID":300254632,"feature_values_id":["CC00503"]}},{"id":"recz1UqPqe3FM8lBi","createdTime":"2022-04-24T21:02:15.000Z","fields":{"term":"haaraccessoire","xml-lang":"nl","feature_values_display_name_en":["recRWNjX0vUT0GqhT"],"AATID":300225910,"feature_values_id":["CC00465"]}},{"id":"recz4F6qnxVCg4jFi","createdTime":"2022-04-24T21:02:15.000Z","fields":{"term":"תלבושות בית ספר","xml-lang":"he","feature_values_display_name_en":["rec4HzMDfqDe4ab3E"],"AATID":300417888,"feature_values_id":["CC00376"]}},{"id":"recz5ER5OvfxSBL57","createdTime":"2022-04-24T21:02:15.000Z","fields":{"term":"toggle","xml-lang":"en","feature_values_display_name_en":["recfIDjXUODWiftM8"],"AATID":300254540,"feature_values_id":["CC00011"]}},{"id":"recz5VVVyLQhbErro","createdTime":"2022-04-24T21:02:15.000Z","fields":{"term":"ascot","xml-lang":"fr","feature_values_display_name_en":["recUKFXvcw2X7Ttud"],"AATID":300210052,"feature_values_id":["CC00028"]}},{"id":"reczAQKM2QZTFVeJy","createdTime":"2022-04-24T21:02:15.000Z","fields":{"term":"costume académique","xml-lang":"fr","feature_values_display_name_en":["recfNjUaXP4ZCogGo"],"AATID":300265060,"feature_values_id":["CC00371"]}},{"id":"reczCDTSxH0yV1EVY","createdTime":"2022-04-24T21:02:15.000Z","fields":{"term":"epaulet","xml-lang":"en","feature_values_display_name_en":["rec135mWCRBOAbArD"],"AATID":300224235,"feature_values_id":["CC00395"]}},{"id":"reczEOppXCkNiTGTV","createdTime":"2022-04-24T21:02:15.000Z","fields":{"term":"coat-dress","xml-lang":"en-gb","feature_values_display_name_en":["recRIsJ9YVQWTaA3C"],"AATID":300209826,"feature_values_id":["CC00323"]}},{"id":"reczGX9sQGfr8OYx4","createdTime":"2022-04-24T21:02:15.000Z","fields":{"term":"peplo","xml-lang":"es","feature_values_display_name_en":["recHEIElmhtQtM6lL"],"AATID":300248709,"feature_values_id":["CC00176"]}},{"id":"reczJaHl2RFMX3hMJ","createdTime":"2022-04-24T21:02:15.000Z","fields":{"term":"shirts (main garments)","xml-lang":"en","feature_values_display_name_en":["recFfCQnHbKVETSUW"],"AATID":300212499,"feature_values_id":["CC00340"]}},{"id":"reczK1EvLcrNsFyde","createdTime":"2022-04-24T21:02:15.000Z","fields":{"term":"alba dalmatica","xml-lang":"en","feature_values_display_name_en":["recrvCSeEUIjjOtQ8"],"AATID":300210431,"feature_values_id":["CC00449"]}},{"id":"reczPlcWgX1y5JsiH","createdTime":"2022-04-24T21:02:15.000Z","fields":{"term":"手帕","xml-lang":"zh-hant","feature_values_display_name_en":["receuMB99dD1mjQjb"],"AATID":300216195,"feature_values_id":["CC00172"]}},{"id":"reczQ1HAgpe4ujdtR","createdTime":"2022-04-24T21:02:15.000Z","fields":{"term":"chaqueta","xml-lang":"es","feature_values_display_name_en":["recVh9T90I9VMfWQJ"],"AATID":300046143,"feature_values_id":["CC00106"]}},{"id":"reczSetGMCYMeNRTz","createdTime":"2022-04-24T21:02:15.000Z","fields":{"term":"rukav","xml-lang":"sr","feature_values_display_name_en":["recXJIVW0FAtERDEV"],"AATID":300210530,"feature_values_id":["CC00358"]}},{"id":"reczT3FjrzqmWs720","createdTime":"2022-04-24T21:02:15.000Z","fields":{"term":"shorts, Bermuda","xml-lang":"en","feature_values_display_name_en":["recaxFbUSF4uX16i9"],"AATID":300221453,"feature_values_id":["CC00439"]}},{"id":"reczTmn5PUg4DUfLS","createdTime":"2022-04-24T21:02:15.000Z","fields":{"term":"slacks","xml-lang":"en","feature_values_display_name_en":["rechoefNv4f2S5IOZ"],"AATID":300209934,"feature_values_id":["CC00435"]}},{"id":"reczVPi2la5euob2I","createdTime":"2022-04-24T21:02:15.000Z","fields":{"term":"polo","xml-lang":"es","feature_values_display_name_en":["recLRonYA3e64IlPb"],"AATID":300209896,"feature_values_id":["CC00041"]}},{"id":"reczckZ9K6ZUXRKJA","createdTime":"2022-04-24T21:02:15.000Z","fields":{"term":"baleinen","xml-lang":"nl","feature_values_display_name_en":["recmFqGWKC7SZTvqA"],"AATID":300253790,"feature_values_id":["CC00199"]}},{"id":"reczeUB6nMGfLDuSo","createdTime":"2022-04-24T21:02:15.000Z","fields":{"term":"stays (costume components)","xml-lang":"en","feature_values_display_name_en":["recmFqGWKC7SZTvqA"],"AATID":300253790,"feature_values_id":["CC00199"]}},{"id":"reczecUoEpvHHCnFR","createdTime":"2022-04-24T21:02:15.000Z","fields":{"term":"rokken","xml-lang":"nl","feature_values_display_name_en":["receEOQdjPyVanseM"],"AATID":300209932,"feature_values_id":["CC00341"]}},{"id":"reczhWB0dTBVr6CYf","createdTime":"2022-04-24T21:02:15.000Z","fields":{"term":"pechera","xml-lang":"es","feature_values_display_name_en":["recTkosG3Q7AVY6tv"],"AATID":300215860,"feature_values_id":["CC00493"]}},{"id":"reczhZYRzhe5McfcK","createdTime":"2022-04-24T21:02:15.000Z","fields":{"term":"jumpers","xml-lang":"nl","feature_values_display_name_en":["rec05HVGPPOLWoyyW"],"AATID":300209900,"feature_values_id":["CC00343"]}},{"id":"recznTBkEC1kv1G7D","createdTime":"2022-04-24T21:02:15.000Z","fields":{"term":"pantalon à sous-pieds","xml-lang":"nl","feature_values_display_name_en":["reclWXtc6qKnIxEDs"],"AATID":300046184,"feature_values_id":["CC00430"]}},{"id":"recznpgu03BWiXIRh","createdTime":"2022-04-24T21:02:15.000Z","fields":{"term":"accessoire de cheveux","xml-lang":"fr","feature_values_display_name_en":["recRWNjX0vUT0GqhT"],"AATID":300225910,"feature_values_id":["CC00465"]}},{"id":"recznu5nfkXKXKcCp","createdTime":"2022-04-24T21:02:15.000Z","fields":{"term":"棉織厚長褲","xml-lang":"zh-hant","feature_values_display_name_en":["recps338NVQb1YNso"],"AATID":300245257,"feature_values_id":["CC00436"]}},{"id":"reczq60XefCvWrULW","createdTime":"2022-04-24T21:02:15.000Z","fields":{"term":"dagkleding","xml-lang":"nl","feature_values_display_name_en":["recRrgHgTz3SO9BKy"],"AATID":300403910,"feature_values_id":["CC00368"]}},{"id":"reczqVFWd9rG96U1R","createdTime":"2022-04-24T21:02:15.000Z","fields":{"term":"Strumpf","xml-lang":"de","feature_values_display_name_en":["recut0JIklzhUvSKB"],"AATID":300209984,"feature_values_id":["CC00605"]}},{"id":"reczx8pS36PdYeKQ0","createdTime":"2022-04-24T21:02:15.000Z","fields":{"term":"vestito da sposa","xml-lang":"it","feature_values_display_name_en":["rec1wGCGk0CNn2XsE"],"AATID":300255177,"feature_values_id":["CC00379"]}},{"id":"reczxqA8Js9DDVBdP","createdTime":"2022-04-24T21:02:15.000Z","fields":{"term":"pantalon capri","xml-lang":"fr","feature_values_display_name_en":["recgOR6DbIBy6tGWq"],"AATID":300221449,"feature_values_id":["CC00423"]}},{"id":"reczzpxrGqRaXU8TO","createdTime":"2022-04-24T21:02:15.000Z","fields":{"term":"spijkerbroek","xml-lang":"nl","feature_values_display_name_en":["recGWKKw4siMvrcgN"],"AATID":300209918,"feature_values_id":["CC00426"]}}]}