{"Content-Type": "image/png", "Content-Length": "69114", "Connection": "close", "x-amz-id-2": "f53ETGn1nH2MdbxwD+L5fXdzzG8G0uV3Ht5hBcV9vhNk/pqlBsaQGdP8ZfeZcTGUCtUWrXKXg1w=", "x-amz-request-id": "58TQCE9036BZ94KN", "Date": "Sun, 30 Apr 2023 17:57:09 GMT", "x-amz-replication-status": "COMPLETED", "Last-Modified": "Fri, 14 Apr 2023 20:40:18 GMT", "ETag": "\"3210c423cffdf52a2181889d281c4b82\"", "x-amz-server-side-encryption": "AES256", "x-amz-version-id": "AydG6BurWW182tc5FNSg2IPbzNqR.nwe", "Accept-Ranges": "bytes", "Server": "AmazonS3", "Content-Security-Policy": "default-src 'none'; style-src 'unsafe-inline'; img-src https://*/favicon.ico; sandbox", "Access-Control-Allow-Origin": "*", "X-Robots-Tag": "none", "Content-Disposition": "inline; filename=\"Imagefromcommons.wikimedia.orgon2023-04-14at4.39.56PM.png\"", "X-Xss-Protection": "1; mode=block", "X-Content-Type-Options": "nosniff", "Referrer-Policy": "no-referrer", "Cache-Control": "max-age=14400, immutable", "X-Cache": "Miss from cloudfront", "Via": "1.1 ebfea1c8ef298b6d415684e80825a276.cloudfront.net (CloudFront)", "X-Amz-Cf-Pop": "EWR52-C1", "X-Amz-Cf-Id": "fdjmltgKQjRoB53ky4xysIBPgWNtp-0cNqHs9zpYOUWMxWEk_Ts5wQ=="}