{"Content-Type": "image/jpeg", "Content-Length": "4269", "Connection": "close", "x-amz-id-2": "gR6kHL/AImleD96D1iwV94u6ACBA0Kl0s9PjRFb++GOCnDQtK1ct6jr5rD5MzHcQ4Io7XiKk/1A=", "x-amz-request-id": "MFY567MBQJBFWFD3", "Date": "Sun, 30 Apr 2023 18:55:53 GMT", "x-amz-replication-status": "FAILED", "Last-Modified": "Fri, 05 Jun 2020 07:35:27 GMT", "ETag": "\"cdefb48b4e50a9dcfdb238781497f9da\"", "x-amz-server-side-encryption": "AES256", "x-amz-version-id": "lZ9v1eEMQ0iN6d5uGpZS_tNzFxy3G91l", "Accept-Ranges": "bytes", "Server": "AmazonS3", "Content-Security-Policy": "default-src 'none'; style-src 'unsafe-inline'; img-src https://*/favicon.ico; sandbox", "Access-Control-Allow-Origin": "*", "X-Robots-Tag": "none", "Content-Disposition": "inline; filename=\"f918e21ca66a4c21190f8dc5565ffa4b.jpg\"", "X-Xss-Protection": "1; mode=block", "X-Content-Type-Options": "nosniff", "Referrer-Policy": "no-referrer", "Cache-Control": "max-age=14400, immutable", "X-Cache": "Hit from cloudfront", "Via": "1.1 2c6ca3b401fc63cf43d9316aff164af4.cloudfront.net (CloudFront)", "X-Amz-Cf-Pop": "EWR52-C1", "X-Amz-Cf-Id": "wrB0It9_uTwtA7uQdn4homOS6diIA3chW1mEninnt2YzH2DsFzz3_g==", "Age": "146"}