{"Content-Type": "image/jpeg", "Content-Length": "29440", "Connection": "close", "x-amz-id-2": "NeURAV7q4deQ4plUMMrJzxX2iSKF+kucUiHzFnhcZ14obekfzdwk4NS+ugyGP57U63pItwwh1pw=", "x-amz-request-id": "0JHEKW2NSV4XQ6MY", "Date": "Mon, 10 Jul 2023 14:46:14 GMT", "x-amz-replication-status": "FAILED", "Last-Modified": "Mon, 12 Oct 2020 01:25:17 GMT", "ETag": "\"336faed130e0de8bbc0f32232d34e44f\"", "x-amz-server-side-encryption": "AES256", "x-amz-version-id": "55OEQhTa8x5PzjPNeTm_k_kQA8JdBick", "Accept-Ranges": "bytes", "Server": "AmazonS3", "Content-Security-Policy": "default-src 'none'; style-src 'unsafe-inline'; img-src https://*/favicon.ico; sandbox", "Access-Control-Allow-Origin": "*", "X-Robots-Tag": "none", "Content-Disposition": "inline; filename=\"CC00165.jpg\"", "X-Xss-Protection": "1; mode=block", "X-Content-Type-Options": "nosniff", "Referrer-Policy": "no-referrer", "Cache-Control": "max-age=14400, immutable", "X-Cache": "Miss from cloudfront", "Via": "1.1 f7c749b4d9ba39d7629c0f2f434dfc76.cloudfront.net (CloudFront)", "X-Amz-Cf-Pop": "IAD55-P1", "X-Amz-Cf-Id": "ufGq0gJY-bxMB0NBvhAmb2B-l2wgIR2a1D4UWW14A5JvuAt36x1kBQ=="}