{"Content-Type": "image/jpeg", "Content-Length": "56783", "Connection": "close", "x-amz-id-2": "mrmX1QiH/3evqrnJuW/J+xStepyQHVF0574Ubd9OrfFHb0zUpOvfmfyf9z8gLZfWl5k25INLok4=", "x-amz-request-id": "0FHQ25ABAF795G9G", "Date": "Mon, 10 Jul 2023 14:46:04 GMT", "x-amz-replication-status": "COMPLETED", "Last-Modified": "Wed, 10 May 2023 17:58:16 GMT", "ETag": "\"d2fe61d9854587e44864d97bd032ad0d\"", "x-amz-server-side-encryption": "AES256", "x-amz-version-id": "z9Bp9j9xOj.PJV9imTt99zI9ZXkGmVco", "Accept-Ranges": "bytes", "Server": "AmazonS3", "Content-Security-Policy": "default-src 'none'; style-src 'unsafe-inline'; img-src https://*/favicon.ico; sandbox", "Access-Control-Allow-Origin": "*", "X-Robots-Tag": "none", "Content-Disposition": "inline; filename=\"Imagefromcommons.wikimedia.orgon2023-05-10at1.58.05PM.jpeg\"", "X-Xss-Protection": "1; mode=block", "X-Content-Type-Options": "nosniff", "Referrer-Policy": "no-referrer", "Cache-Control": "max-age=14400, immutable", "X-Cache": "Miss from cloudfront", "Via": "1.1 ebd7b246dc1b8bef0a7a10752563dc62.cloudfront.net (CloudFront)", "X-Amz-Cf-Pop": "IAD55-P1", "X-Amz-Cf-Id": "ir2KxVybBc59nYoTTOYcMXtHzWylPYMY7E97cYZRxr8jzkBEOoIjDQ=="}