{"Content-Type": "image/jpeg", "Content-Length": "71421", "Connection": "close", "x-amz-id-2": "RBQpCNwSKN81aSKbxWZg2iOEvYT7Dh8L+N9IhNxZMcaHU/P5DwFNJ3XBlZ5dfPst8TLK/trGCyc=", "x-amz-request-id": "PDG5ZV3HN1F2HM6Z", "Date": "Sun, 30 Apr 2023 18:55:54 GMT", "x-amz-replication-status": "FAILED", "Last-Modified": "Thu, 09 Apr 2020 23:10:48 GMT", "ETag": "\"24dce42638acb30a8710a95c040110a6\"", "x-amz-server-side-encryption": "AES256", "x-amz-version-id": "pRLCNZJJ7UYDZ8.HERFD9YO84dyPnE6y", "Accept-Ranges": "bytes", "Server": "AmazonS3", "Content-Security-Policy": "default-src 'none'; style-src 'unsafe-inline'; img-src https://*/favicon.ico; sandbox", "Access-Control-Allow-Origin": "*", "X-Robots-Tag": "none", "Content-Disposition": "inline; filename=\"1840_0_226.jpg\"", "X-Xss-Protection": "1; mode=block", "X-Content-Type-Options": "nosniff", "Referrer-Policy": "no-referrer", "Cache-Control": "max-age=14400, immutable", "X-Cache": "Hit from cloudfront", "Via": "1.1 777c0716c0ef8010208c3559195306d6.cloudfront.net (CloudFront)", "X-Amz-Cf-Pop": "EWR52-C1", "X-Amz-Cf-Id": "j4ibXpsrwXRDdiaeSGi3RxMUKL8xHWhe7_yrDi0CM-xnZ3tTDDtyaw==", "Age": "146"}